{
  "sections": {
    "image_banner": {
      "type": "image-banner",
      "settings": {
        "image": "shopify:\/\/shop_images\/keyvisual-fairings-herbst-2022.jpg",
        "image_overlay_opacity": 0,
        "image_height": "large",
        "adapt_height_first_image": true,
        "desktop_content_position": "bottom-center",
        "show_text_box": false,
        "desktop_content_alignment": "center",
        "color_scheme": "background-1",
        "mobile_content_alignment": "center",
        "stack_images_on_mobile": false,
        "show_text_below": false
      }
    },
    "ffe33e2d-5b38-4356-9ec8-3f599006a4a6": {
      "type": "custom-liquid",
      "settings": {
        "custom_liquid": "<div class=\"page-width\">\n<div class=\"tiles-container\">\n  \n  <div class=\"tile tile-eins\">\n    \n<div class=\"tile-image\">\n<a href=\"\" target=\"_blank\">     <img src=\"https:\/\/icletta.com\/images\/Webshop\/ICE-liegerad.jpg\"><\/a>\n    <\/div>\n  <a href=\"\" target=\"_blank\"> <div class=\"tile-button\">\n      <span class=\"button-text\">ICE Ersatzteile<\/span><\/a>\n    <\/div>\n    <\/div>\n  <div class=\"tile tile-zwei\">\n  <div class=\"tile-image\">\n    <img src=\"https:\/\/icletta.com\/images\/Webshop\/liegerad-kettenleitrollen.jpg\">\n    <\/div>\n    <div class=\"tile-button\">\n      <span class=\"button-text\">T-Cycle Kettenleitrollen<\/span>\n  <\/div>\n  <\/div>\n  <div class=\"tile tile-drei\">\n  <div class=\"tile-image\">\n      <img src=\"https:\/\/icletta.com\/images\/Webshop\/liegerad-frontverkleidung.jpg\">\n    <\/div>\n    <div class=\"tile-button\">\n      <span class=\"button-text\">T-Cycle Frontverkleidungen<\/span>\n    <\/div>\n  <\/div>\n  <div class=\"tile tile-vier\">\n <div class=\"tile-image\">\n      <img src=\"https:\/\/icletta.com\/images\/Webshop\/liegerad-selbstbau.jpg\">\n    <\/div>\n <div class=\"tile-button\">\n      <span class=\"button-text\">Liegerad Selbstbau<\/span>\n    <\/div>\n  <\/div>\n  <div class=\"tile tile-fuenf\">\n  <div class=\"tile-image\">\n      <img src=\"https:\/\/icletta.com\/images\/Webshop\/liegerad-sitze.jpg\">\n    <\/div>\n    <div class=\"tile-button\">\n      <span class=\"button-text\">Trike Sitzkomfort<\/span>\n    <\/div>\n  <\/div>\n  <div class=\"tile tile-sechs\">\n  <div class=\"tile-image\">\n      <img src=\"https:\/\/icletta.com\/images\/Webshop\/liegerad-laufradbau.jpg\" >\n    <\/div>\n    <div class=\"tile-button\">\n      <span class=\"button-text\">Liegerad Laufradbau<\/span>\n    <\/div>\n  <\/div>\n  <div class=\"tile tile-sieben\">\n  <div class=\"tile-image\">\n      <img src=\"https:\/\/icletta.com\/images\/Webshop\/t-cycle-zubehoerhalter.jpg\">\n    <\/div>\n <div class=\"tile-button\">\n      <span class=\"button-text\">T-Cycle Zubehörhalter<\/span>\n    <\/div>\n  <\/div>\n<\/div>\n<\/div>",
        "color_scheme": "background-1",
        "padding_top": 40,
        "padding_bottom": 52
      }
    },
    "featured_collection": {
      "type": "featured-collection",
      "settings": {
        "title": "",
        "heading_size": "h2",
        "description": "",
        "show_description": false,
        "description_style": "body",
        "collection": "all",
        "products_to_show": 4,
        "columns_desktop": 4,
        "full_width": false,
        "show_view_all": false,
        "view_all_style": "solid",
        "enable_desktop_slider": false,
        "color_scheme": "background-1",
        "image_ratio": "adapt",
        "show_secondary_image": true,
        "show_vendor": false,
        "show_rating": false,
        "enable_quick_add": false,
        "columns_mobile": "2",
        "swipe_on_mobile": false,
        "padding_top": 28,
        "padding_bottom": 36
      }
    },
    "b5cd2511-d36c-418c-9d3a-615783d1e6ca": {
      "type": "custom-liquid",
      "settings": {
        "custom_liquid": "<div class=\"page-width button-container\">\n<a href=\"https:\/\/icletta-liegerad-zubehor.myshopify.com\/collections\/marke-ice\/\">\n<div class=\"ICE-button\">\n  Zu den ICE Produkten &#10132;<\/div><\/a><\/div>",
        "color_scheme": "background-1",
        "padding_top": 40,
        "padding_bottom": 52
      }
    },
    "0fe1796e-fe07-4c90-9b06-4a6a193e2996": {
      "type": "multicolumn",
      "blocks": {
        "template--16752291545376__0fe1796e-fe07-4c90-9b06-4a6a193e2996-1669197272f1478b88-0": {
          "type": "column",
          "settings": {
            "image": "shopify:\/\/shop_images\/ukshipping.jpg",
            "title": "",
            "text": "",
            "link_label": "",
            "link": ""
          }
        },
        "template--16752291545376__0fe1796e-fe07-4c90-9b06-4a6a193e2996-1669197272f1478b88-1": {
          "type": "column",
          "settings": {
            "image": "shopify:\/\/shop_images\/Trike-Warenkorb-delivery_91fccde6-139b-45bf-b6ba-c24bf43a2737.png",
            "title": "",
            "text": "<p>Wir versenden alle Bestellungen per DHL<\/p><p><strong>Deutschland:<\/strong> 6,90 Euro<br\/><strong>Europäische Union:<\/strong> 9,90 Euro<br\/><strong>CH \/ NO \/ UK:<\/strong> 19,90 Euro<\/p>",
            "link_label": "",
            "link": ""
          }
        },
        "template--16752291545376__0fe1796e-fe07-4c90-9b06-4a6a193e2996-1669197272f1478b88-2": {
          "type": "column",
          "settings": {
            "image": "shopify:\/\/shop_images\/ice-elastomer-tabelle.jpg",
            "title": "Column",
            "text": "<p>Pair text with an image to focus on your chosen product, collection, or blog post. Add details on availability, style, or even provide a review.<\/p>",
            "link_label": "",
            "link": ""
          }
        }
      },
      "block_order": [
        "template--16752291545376__0fe1796e-fe07-4c90-9b06-4a6a193e2996-1669197272f1478b88-0",
        "template--16752291545376__0fe1796e-fe07-4c90-9b06-4a6a193e2996-1669197272f1478b88-1",
        "template--16752291545376__0fe1796e-fe07-4c90-9b06-4a6a193e2996-1669197272f1478b88-2"
      ],
      "settings": {
        "title": "Multicolumn",
        "heading_size": "h1",
        "image_width": "full",
        "image_ratio": "adapt",
        "columns_desktop": 3,
        "column_alignment": "left",
        "background_style": "primary",
        "button_label": "Button label",
        "button_link": "",
        "color_scheme": "background-1",
        "columns_mobile": "1",
        "swipe_on_mobile": false,
        "padding_top": 36,
        "padding_bottom": 36
      }
    },
    "09e28f4b-ccb4-4b57-94fb-dd018bd83cdd": {
      "type": "custom-liquid",
      "settings": {
        "custom_liquid": "<body style=\"background-color:lightgrey;\">\n<\/body>\n<div class=\"page-width\">\n<div class=\"vorschaubox\">\n  <div class=\"vorschaubox-thumb\">\n    <img        src=\"https:\/\/cdn.shopify.com\/s\/files\/1\/0667\/7725\/2128\/files\/tw-kettenleitrolle.jpg\" alt=\"Test\"\/>\n  <\/div>\n  <div class=\"vorschaubox-info\">\n    <div class=\"name\">      \n    <\/div>\n    <div class=\"vorschaubox-box-heading\">\n      <h1>T-Cycle Firmenportrait<\/h1>\n    <\/div>\n    <div class=\"vorschaubox-box\">\n     Auf dieser Seite erfahren Sie alles über den Liegeradzubehör\nSpezialisten aus den USA. ICLETTA vertreibt seit nunmehr fünfzehn Jahren die aufwändig gefrästen Anbauteile von T-Cycle in ganz Europa. Lernen Sie jetzt die Entstehungsgeschichte des familiär gehaltenen\nUnternehmens und die Gesichter hinter den Produkten kennen.\n     <\/div>\n    <a href=\"\/pages\/t-cycle-firmenportrait\" alt=\"Entdecken Sie die Geschichte von TerraCycle\"> <div class=\"vorschaubox-button\">\n      Erfahren Sie mehr\n     <\/div><\/a>\n    <\/div>\n   <\/div>\n<\/div>\n<\/div>",
        "color_scheme": "background-1",
        "padding_top": 40,
        "padding_bottom": 52
      }
    },
    "e298752e-f10f-4baa-adcc-564701e93d51": {
      "type": "rich-text",
      "blocks": {
        "template--16752291545376__e298752e-f10f-4baa-adcc-564701e93d51-1668681435fae0d837-0": {
          "type": "heading",
          "settings": {
            "heading": "<p>Willkommen in der ICLETTA Themenwelt<\/p>",
            "heading_size": "h1"
          }
        }
      },
      "block_order": [
        "template--16752291545376__e298752e-f10f-4baa-adcc-564701e93d51-1668681435fae0d837-0"
      ],
      "settings": {
        "desktop_content_position": "center",
        "content_alignment": "center",
        "color_scheme": "accent-1",
        "full_width": true,
        "padding_top": 20,
        "padding_bottom": 20,
        "content_width": "default"
      }
    },
    "c5146bc4-d7c5-49dd-9165-affbdec0dfaa": {
      "type": "image-with-text",
      "blocks": {
        "template--16752291545376__c5146bc4-d7c5-49dd-9165-affbdec0dfaa-1668679157686d7e7f-0": {
          "type": "heading",
          "settings": {
            "heading": "T-Cycle Firmenportrait",
            "heading_size": "h1"
          }
        },
        "template--16752291545376__c5146bc4-d7c5-49dd-9165-affbdec0dfaa-1668679157686d7e7f-1": {
          "type": "text",
          "settings": {
            "text": "<p>Auf dieser Seite erfahren Sie alles über den Liegeradzubehör <br\/>Spezialisten aus den USA. ICLETTA vertreibt seit nunmehr fünfzehn Jahren die aufwändig gefrästen Anbauteile von T-Cycle in ganz Europa. Lernen Sie jetzt die Entstehungsgeschichte des familiär gehaltenen <br\/>Unternehmens und die Gesichter hinter den Produkten kennen.<\/p>",
            "text_style": "body"
          }
        },
        "template--16752291545376__c5146bc4-d7c5-49dd-9165-affbdec0dfaa-1668679157686d7e7f-2": {
          "type": "button",
          "settings": {
            "button_label": "Erfahren Sie mehr",
            "button_link": "shopify:\/\/pages\/t-cycle-firmenportrait"
          }
        }
      },
      "block_order": [
        "template--16752291545376__c5146bc4-d7c5-49dd-9165-affbdec0dfaa-1668679157686d7e7f-0",
        "template--16752291545376__c5146bc4-d7c5-49dd-9165-affbdec0dfaa-1668679157686d7e7f-1",
        "template--16752291545376__c5146bc4-d7c5-49dd-9165-affbdec0dfaa-1668679157686d7e7f-2"
      ],
      "settings": {
        "image": "shopify:\/\/shop_images\/tw-firmenportrait.jpg",
        "height": "small",
        "desktop_image_width": "small",
        "layout": "image_first",
        "desktop_content_position": "middle",
        "desktop_content_alignment": "left",
        "content_layout": "no-overlap",
        "color_scheme": "background-1",
        "mobile_content_alignment": "center",
        "padding_top": 36,
        "padding_bottom": 36
      }
    },
    "b51dec6b-3962-4f0c-a2c3-e5b7d92cd0e0": {
      "type": "image-with-text",
      "blocks": {
        "template--16752291545376__b51dec6b-3962-4f0c-a2c3-e5b7d92cd0e0-1668679157686d7e7f-0": {
          "type": "heading",
          "settings": {
            "heading": "T-Cycle Kettenleitrollen",
            "heading_size": "h1"
          }
        },
        "template--16752291545376__b51dec6b-3962-4f0c-a2c3-e5b7d92cd0e0-1668679157686d7e7f-1": {
          "type": "text",
          "settings": {
            "text": "<p>Sie hat schon immer das Innenleben einer Kettenleitrolle interessiert? Auf dieser Seite beantworten wir alle Fragen zu unseren CNC gefrästen Tuningrollen. Lernen Sie die Vorzüge der verschiedenen Ausführungen kennen und entdecken Sie, welche Rolle zu ihrem Liegerad passt.<\/p>",
            "text_style": "body"
          }
        },
        "template--16752291545376__b51dec6b-3962-4f0c-a2c3-e5b7d92cd0e0-1668679157686d7e7f-2": {
          "type": "button",
          "settings": {
            "button_label": "Erfahren Sie mehr",
            "button_link": "shopify:\/\/pages\/t-cycle-kettenleitrollen"
          }
        }
      },
      "block_order": [
        "template--16752291545376__b51dec6b-3962-4f0c-a2c3-e5b7d92cd0e0-1668679157686d7e7f-0",
        "template--16752291545376__b51dec6b-3962-4f0c-a2c3-e5b7d92cd0e0-1668679157686d7e7f-1",
        "template--16752291545376__b51dec6b-3962-4f0c-a2c3-e5b7d92cd0e0-1668679157686d7e7f-2"
      ],
      "settings": {
        "image": "shopify:\/\/shop_images\/tw-kettenleitrolle.jpg",
        "height": "small",
        "desktop_image_width": "small",
        "layout": "image_first",
        "desktop_content_position": "middle",
        "desktop_content_alignment": "left",
        "content_layout": "no-overlap",
        "color_scheme": "background-1",
        "mobile_content_alignment": "center",
        "padding_top": 36,
        "padding_bottom": 36
      }
    },
    "531902d4-1772-4c6e-9168-fe440a37f650": {
      "type": "multicolumn",
      "blocks": {
        "template--16694958162208__531902d4-1772-4c6e-9168-fe440a37f650-1666618168e77441f1-0": {
          "type": "column",
          "settings": {
            "image": "shopify:\/\/shop_images\/IclettaLogo.png",
            "title": "",
            "text": "<p>Der Name ICLETTA leitet sich ursprünglich aus dem Romanischen ab. Bicicletta - bicyclette - bicicletta bedeutet in mehreren Sprachen einfach \"Zweirad\". Auch das Englische lehnt sich mit „bicycle“ an den romanischen Wortstamm an. ICLETTA ist ein Kunstwort, das für die Anzahl der tatsächlichen Räder alle Optionen offen lässt.<\/p>",
            "link_label": "",
            "link": ""
          }
        },
        "template--16694958162208__531902d4-1772-4c6e-9168-fe440a37f650-1666618168e77441f1-1": {
          "type": "column",
          "settings": {
            "title": "Warum wir",
            "text": "<p>Unser Engagement gilt der Fahrradkultur. Wir haben Spaß an unserer Arbeit. Und wir hoffen, dass Sie sich von unserer Begeisterung anstecken lassen. Wir wollen alle Liegerad- und Liegedreiradfahrer und solche, die es noch werden möchten, für unsere ausgereiften ICE Trikes und unsere praktischen Anbauteile begeistern. Egal ob Sie gerade die ersten Schritte zu deinem eigenen Liege- oder Dreirad unternehmen, oder bereits schon ein langjähriger Enthusiast sind: Bei uns finden Sie das passende Angebot.<\/p>",
            "link_label": "",
            "link": ""
          }
        }
      },
      "block_order": [
        "template--16694958162208__531902d4-1772-4c6e-9168-fe440a37f650-1666618168e77441f1-0",
        "template--16694958162208__531902d4-1772-4c6e-9168-fe440a37f650-1666618168e77441f1-1"
      ],
      "settings": {
        "title": "Über uns",
        "heading_size": "h1",
        "image_width": "half",
        "image_ratio": "adapt",
        "columns_desktop": 2,
        "column_alignment": "center",
        "background_style": "none",
        "button_label": "",
        "button_link": "",
        "color_scheme": "background-1",
        "columns_mobile": "1",
        "swipe_on_mobile": false,
        "padding_top": 36,
        "padding_bottom": 36
      }
    }
  },
  "order": [
    "image_banner",
    "ffe33e2d-5b38-4356-9ec8-3f599006a4a6",
    "featured_collection",
    "b5cd2511-d36c-418c-9d3a-615783d1e6ca",
    "0fe1796e-fe07-4c90-9b06-4a6a193e2996",
    "09e28f4b-ccb4-4b57-94fb-dd018bd83cdd",
    "e298752e-f10f-4baa-adcc-564701e93d51",
    "c5146bc4-d7c5-49dd-9165-affbdec0dfaa",
    "b51dec6b-3962-4f0c-a2c3-e5b7d92cd0e0",
    "531902d4-1772-4c6e-9168-fe440a37f650"
  ]
}
